CHANGELOG.txt
MANIFEST.in
README.md
README.txt
setup.py
dot3k/__init__.py
dot3k/backlight.py
dot3k/joystick.py
dot3k/lcd.py
dot3k/menu.py
dot3k.egg-info/PKG-INFO
dot3k.egg-info/SOURCES.txt
dot3k.egg-info/dependency_links.txt
dot3k.egg-info/requires.txt
dot3k.egg-info/top_level.txt
dothat/__init__.py
dothat/backlight.py
dothat/lcd.py
dothat/touch.py