Metadata-Version: 1.1
Name: dot3k
Version: 2.0.1
Summary: Display-o-Tron 3000 Driver
Home-page: http://www.pimoroni.com
Author: Philip Howard
Author-email: phil@pimoroni.com
License: MIT
Keywords: Raspberry Pi ST7036 SN3218 LCD
Platform: UNKNOWN
Classifier: Development Status :: 5 - Production/Stable
Classifier: Operating System :: POSIX :: Linux
Classifier: License :: OSI Approved :: MIT License
Classifier: Intended Audience :: Developers
Classifier: Programming Language :: Python :: 2.6
Classifier: Programming Language :: Python :: 2.7
Classifier: Programming Language :: Python :: 3
Classifier: Topic :: Software Development
Classifier: Topic :: System :: Hardware
